BaseExtensions/Attributes.py
BaseExtensions/AutoCounter.py
BaseExtensions/Constants.py
BaseExtensions/Dates.py
BaseExtensions/Files.py
BaseExtensions/Helpers.py
BaseExtensions/Images.py
BaseExtensions/Logging.py
BaseExtensions/Setup.py
BaseExtensions/Threads.py
BaseExtensions/__init__.py
BaseExtensions/__version__.py
BaseExtensions/sizes.py
BaseExtensions/Models/Json.py
BaseExtensions/Models/MixIns.py
BaseExtensions/Models/__init__.py
BaseExtensions-1.2.6.dist-info/LICENSE.md
BaseExtensions-1.2.6.dist-info/METADATA
BaseExtensions-1.2.6.dist-info/WHEEL
BaseExtensions-1.2.6.dist-info/top_level.txt
BaseExtensions-1.2.6.dist-info/RECORD
